{
  "version": "0.2.1",
  "defaults": {},
  "configurations": [
    {
      "type": "default",
      "project": "CMakeLists.txt",
      "projectTarget": "erase_specify_color.exe (erase_specify_color\\erase_specify_color.exe)",
      "name": "erase_specify_color.exe (erase_specify_color\\erase_specify_color.exe)",
      "args": [
        "C:\\Users\\Quenwaz\\Pictures\\IMG\\3.jpg"
      ],
      "env": {
        "DEBUG_LOGGING_LEVEL": "trace;info",
        "ENABLE_TRACING": "true",
        "PATH": "${env.PATH};E:/DevEnvs/Cpp/opencvsdk/x64/bind"
      }
    }
  ]
}